colav_unsafe_set_gen/main.py
colav_unsafe_set_gen/indices_of_interest/__init__.py
colav_unsafe_set_gen/indices_of_interest/indices_of_interest.py
colav_unsafe_set_gen/indices_of_interest/unionise_indices_of_interest.py
colav_unsafe_set_gen/objects/__init__.py
colav_unsafe_set_gen/objects/configuration.py
colav_unsafe_set_gen/objects/dynamic_object.py
colav_unsafe_set_gen/objects/dynamic_obstacle.py
colav_unsafe_set_gen/objects/dynamic_obstacle_with_metrics.py
colav_unsafe_set_gen/risk_assessment/__init__.py
colav_unsafe_set_gen/risk_assessment/risk_assessment.py
colav_unsafe_set_gen/unsafe_set/__init__.py
colav_unsafe_set_gen/unsafe_set/unsafe_set.py
colav_unsafe_set_gen-0.0.8.dist-info/LICENSE
colav_unsafe_set_gen-0.0.8.dist-info/METADATA
colav_unsafe_set_gen-0.0.8.dist-info/WHEEL
colav_unsafe_set_gen-0.0.8.dist-info/top_level.txt
colav_unsafe_set_gen-0.0.8.dist-info/RECORD
