Metadata-Version: 2.2
Name: colav_unsafe_set_gen
Version: 0.0.8
Summary: A custom unsafe_set generator for dynamic vessels based on COLAV: Indices of interest.
Author-email: Ryan <r.mckee@qub.ac.uk>
License: MIT License
Classifier: Programming Language :: Python :: 3
Classifier: Operating System :: OS Independent
Requires-Python: >=3.10
License-File: LICENSE
Requires-Dist: scipy<2.0.0,>=1.15.1
Requires-Dist: numpy<3.0.0,>=2.2.3
